k7eel/__init__.py
k7eel/main.py
nukebount-0.1.1.dist-info/METADATA
nukebount-0.1.1.dist-info/WHEEL
nukebount-0.1.1.dist-info/entry_points.txt
nukebount-0.1.1.dist-info/top_level.txt
nukebount-0.1.1.dist-info/RECORD
